windows_tools.signtool-0.6.2-py3.12-nspkg.pth
windows_tools/signtool/__init__.py
windows_tools.signtool-0.6.2.dist-info/LICENSE
windows_tools.signtool-0.6.2.dist-info/METADATA
windows_tools.signtool-0.6.2.dist-info/WHEEL
windows_tools.signtool-0.6.2.dist-info/namespace_packages.txt
windows_tools.signtool-0.6.2.dist-info/top_level.txt
windows_tools.signtool-0.6.2.dist-info/RECORD
