Metadata-Version: 2.1
Name: windows_tools.signtool
Version: 0.6.2
Summary: Windows authenticode signature tool
Home-page: https://github.com/netinvent/windows_tools
Author: NetInvent - Orsiris de Jong
Author-email: contact@netinvent.fr
Keywords: wmi,virtualization,file,acl,ntfs,refs,antivirus,security,firewall,office
Classifier: Development Status :: 5 - Production/Stable
Classifier: Intended Audience :: Developers
Classifier: Topic :: Software Development
Classifier: Topic :: System
Classifier: Topic :: System :: Operating System
Classifier: Topic :: System :: Shells
Classifier: Programming Language :: Python
Classifier: Programming Language :: Python :: 3
Classifier: Programming Language :: Python :: Implementation :: CPython
Classifier: Programming Language :: Python :: Implementation :: PyPy
Classifier: Operating System :: Microsoft
Classifier: Operating System :: Microsoft :: Windows
Classifier: License :: OSI Approved :: BSD License
Requires-Python: >=3.5
License-File: LICENSE
Requires-Dist: ofunctions.file-utils >=1.0.2
Requires-Dist: ofunctions.network >=1.3.2
Requires-Dist: command-runner >=1.2.1
Requires-Dist: windows-tools.bitness >=0.2.1
Requires-Dist: ofunctions.file-utils
Requires-Dist: ofunctions.network >=1.6.3
